models/README.md
models/hybrid.pkl
models/lexical.pkl
models/lexical_plus.pkl
models/training/README.md
models/training/train_and_evaluate_hybrid_model.py
models/training/data/README.md
models/training/logs/hybrid_log.txt
models/training/nl4opt_utils/README.md
models/training/nl4opt_utils/__init__.py
models/training/nl4opt_utils/metric.py
models/training/nl4opt_utils/reader.py
models/training/nl4opt_utils/reader_utils.py
models/training/nl4opt_utils/utils.py
models/training/notebooks/README.md
models/training/notebooks/data_augmentation.ipynb
models/training/notebooks/entity_gazetteers.ipynb
ner4opt/__init__.py
ner4opt/_version.py
ner4opt/constants.py
ner4opt/featurizer.py
ner4opt/ner4opt.py
ner4opt/setup_nltk.py
ner4opt/setup_spacy.py
ner4opt/utils.py
tests/__init__.py
tests/test_features.py
tests/test_ner4opt.py
tests/test_utils.py
tests/fixtures/example_problem.txt
tests/fixtures/hybrid_result.json
tests/fixtures/lexical_plus_result.json
tests/fixtures/lexical_result.json
tests/fixtures/semantic_result.json
ner4opt-1.0.5.dist-info/LICENSE
ner4opt-1.0.5.dist-info/METADATA
ner4opt-1.0.5.dist-info/WHEEL
ner4opt-1.0.5.dist-info/top_level.txt
ner4opt-1.0.5.dist-info/RECORD
