Metadata-Version: 2.1
Name: ner4opt
Version: 1.0.5
Summary: NER4OPT Library
Home-page: https://github.com/skadio/ner4opt
Project-URL: Source, https://github.com/skadio/ner4opt
Classifier: License :: OSI Approved :: MIT License
Classifier: Programming Language :: Python :: 3.8
Classifier: Operating System :: OS Independent
Requires-Python: >=3.8,<3.9
License-File: LICENSE
Requires-Dist: inflect
Requires-Dist: nltk
Requires-Dist: overrides
Requires-Dist: pandas
Requires-Dist: simpletransformers ==0.63.7
Requires-Dist: tokenizers ==0.12.1
Requires-Dist: spacy ==3.2.0
Requires-Dist: spacy-transformers ==1.1.7
Requires-Dist: sklearn-crfsuite ==0.3.6
Requires-Dist: torch ==1.12.0
Requires-Dist: typing-extensions ==4.4.0
